full_adder/full_adder.v
module full_adder(a,b,c,sum,carry);
input a,b,c;
output sum,carry;

assign sum = a ^ b ^ c;
assign carry = (a & b) | (b & c) | (a & c);

endmodule

full_adder/full_adder_tb.v
`include "full_adder.v"
module full_adder_tb();
reg a,b,c;
wire sum,carry;

full_adder uut (.a(a), .b(b), .c(c), .sum(sum), .carry(carry));

initial begin
    $dumpfile("full_adder.vcd");
    $dumpvars(0, full_adder_tb);

    #10 a = 0; b = 0; c = 0;
    #10 a = 0; b = 0; c = 1;
    #10 a = 0; b = 1; c = 0;
    #10 a = 0; b = 1; c = 1;
    #10 a = 1; b = 0; c = 0;
    #10 a = 1; b = 0; c = 1;
    #10 a = 1; b = 1; c = 0;
    #10 a = 1; b = 1; c = 1;

    #1 $monitor ("sum = %b", "carry = %b", sum, carry);

end
endmodule

full_adder/full_adder.vcd
$date
	Thu Feb 29 02:09:29 2024
$end
$version
	Icarus Verilog
$end
$timescale
	1s
$end
$scope module full_adder_tb $end
$var wire 1 ! sum $end
$var wire 1 " carry $end
$var reg 1 # a $end
$var reg 1 $ b $end
$var reg 1 % c $end
$scope module uut $end
$var wire 1 # a $end
$var wire 1 $ b $end
$var wire 1 % c $end
$var wire 1 " carry $end
$var wire 1 ! sum $end
$upscope $end
$upscope $end
$enddefinitions $end
#0
$dumpvars
x%
x$
x#
x"
x!
$end
#10
0"
0!
0%
0$
0#
#20
1!
1%
#30
0%
1$
#40
1"
0!
1%
#50
0"
1!
0%
0$
1#
#60
1"
0!
1%
#70
0%
1$
#80
1!
1%
